alf_t5/__init__.py
alf_t5/app.py
alf_t5/data.py
alf_t5/dataset.py
alf_t5/evaluation.py
alf_t5/experiment.py
alf_t5/translator.py
alf_t5/utils.py
alf_t5-1.1.3.dist-info/entry_points.txt
alf_t5-1.1.3.dist-info/LICENSE
alf_t5-1.1.3.dist-info/METADATA
alf_t5-1.1.3.dist-info/WHEEL
alf_t5-1.1.3.dist-info/RECORD
