Metadata-Version: 2.3
Name: alf-t5
Version: 1.1.3
Summary: ALF-T5 - Adaptative Language Framework for T5 is a Machine Learning framework for Neural Machine Translation Systems training and, subsequently, bidirectional translation.
License: MIT
Author: Matheus Silva
Author-email: matjsz42@gmail.com
Requires-Python: >=3.11
Classifier: License :: OSI Approved :: MIT License
Classifier: Programming Language :: Python :: 3
Classifier: Programming Language :: Python :: 3.11
Classifier: Programming Language :: Python :: 3.12
Classifier: Programming Language :: Python :: 3.13
Requires-Dist: matplotlib (>=3.7.0)
Requires-Dist: nltk (>=3.8.0)
Requires-Dist: numpy (>=1.24.0)
Requires-Dist: pandas (>=2.0.0)
Requires-Dist: peft (>=0.5.0)
Requires-Dist: sentencepiece (>=0.1.99)
Requires-Dist: torch (>=2.0.0)
Requires-Dist: tqdm (>=4.66.0)
Requires-Dist: transformers (>=4.30.0)
